GPMAuto/__init__.py
GPMAuto/GPMLoginAPI/GPMLoginAPI.py
GPMAuto/GPMLoginAPI/__init__.py
GPMAuto/GPMLoginAPI/start_profile.py
GPMAuto/SeleniumGPM/__init__.py
GPMAuto/SeleniumGPM/geometry.py
GPMAuto/SeleniumGPM/pointer.py
GPMAuto/SeleniumGPM/selenium_gpm.py
GPMAuto-0.1.3.dist-info/METADATA
GPMAuto-0.1.3.dist-info/WHEEL
GPMAuto-0.1.3.dist-info/top_level.txt
GPMAuto-0.1.3.dist-info/RECORD
