Metadata-Version: 2.1
Name: GPMAuto
Version: 0.1.3
Summary: API GPMLogin and Selenium Custom
Home-page: https://github.com/chi2911ks
Author: chi2911ks
Author-email: chi2911bs@gmail.com
